odoo/addons/sale_order_import/README.rst
odoo/addons/sale_order_import/__init__.py
odoo/addons/sale_order_import/__manifest__.py
odoo/addons/sale_order_import/i18n/es.po
odoo/addons/sale_order_import/i18n/fr.po
odoo/addons/sale_order_import/i18n/it.po
odoo/addons/sale_order_import/i18n/sale_order_import.pot
odoo/addons/sale_order_import/models/__init__.py
odoo/addons/sale_order_import/models/sale.py
odoo/addons/sale_order_import/readme/CONTRIBUTORS.md
odoo/addons/sale_order_import/readme/CREDITS.md
odoo/addons/sale_order_import/readme/DESCRIPTION.md
odoo/addons/sale_order_import/readme/USAGE.md
odoo/addons/sale_order_import/security/ir.model.access.csv
odoo/addons/sale_order_import/static/description/icon.png
odoo/addons/sale_order_import/static/description/index.html
odoo/addons/sale_order_import/tests/__init__.py
odoo/addons/sale_order_import/tests/common.py
odoo/addons/sale_order_import/tests/test_order_import.py
odoo/addons/sale_order_import/tests/test_parse_validate.py
odoo/addons/sale_order_import/tests/test_sale_order.py
odoo/addons/sale_order_import/tests/fixtures/test.pdf
odoo/addons/sale_order_import/wizard/__init__.py
odoo/addons/sale_order_import/wizard/sale_order_import.py
odoo/addons/sale_order_import/wizard/sale_order_import_view.xml
odoo_addon_sale_order_import-18.0.1.0.1.dist-info/METADATA
odoo_addon_sale_order_import-18.0.1.0.1.dist-info/WHEEL
odoo_addon_sale_order_import-18.0.1.0.1.dist-info/top_level.txt
odoo_addon_sale_order_import-18.0.1.0.1.dist-info/RECORD
