Metadata-Version: 2.1
Name: odoo-addon-sale_order_import
Version: 18.0.1.0.1
Requires-Python: >=3.10
Requires-Dist: odoo-addon-base_business_document_import==18.0.*
Requires-Dist: odoo-addon-onchange_helper==18.0.*
Requires-Dist: odoo-addon-pdf_xml_attachment==18.0.*
Requires-Dist: odoo-addon-sale_commercial_partner==18.0.*
Requires-Dist: odoo==18.0.*
Summary: Import RFQ or sale orders from files
Home-page: https://github.com/OCA/edi
License: AGPL-3
Author: Akretion, Camptocamp, Odoo Community Association (OCA)
Author-email: support@odoo-community.org
Classifier: Programming Language :: Python
Classifier: Framework :: Odoo
Classifier: Framework :: Odoo :: 18.0
Classifier: License :: OSI Approved :: GNU Affero General Public License v3
